README.md
setup.py
InvestOpenDataTools.egg-info/PKG-INFO
InvestOpenDataTools.egg-info/SOURCES.txt
InvestOpenDataTools.egg-info/dependency_links.txt
InvestOpenDataTools.egg-info/requires.txt
InvestOpenDataTools.egg-info/top_level.txt
opendatatools/__init__.py
opendatatools/amac/__init__.py
opendatatools/amac/amac_agent.py
opendatatools/amac/amac_interface.py
opendatatools/aqi/__init__.py
opendatatools/aqi/aqi_agent.py
opendatatools/aqi/aqi_interface.py
opendatatools/aqi/constant.py
opendatatools/aqi2/__init__.py
opendatatools/aqi2/aqi2_agent.py
opendatatools/aqi2/aqi2_interface.py
opendatatools/aqi2/constant.py
opendatatools/aqi2/util.py
opendatatools/coin/__init__.py
opendatatools/coin/coin_agent.py
opendatatools/coin/coin_interface.py
opendatatools/common/__init__.py
opendatatools/common/date_util.py
opendatatools/common/md5_util.py
opendatatools/common/rest_agent.py
opendatatools/common/string_util.py
opendatatools/common/ui_util.py
opendatatools/datayes/__init__.py
opendatatools/datayes/datayes_interface.py
opendatatools/datayes/robo_agent.py
opendatatools/economy/__init__.py
opendatatools/economy/economy_interface.py
opendatatools/economy/nbs_agent.py
opendatatools/fund/__init__.py
opendatatools/fund/fund_agent.py
opendatatools/fund/fund_interface.py
opendatatools/futures/__init__.py
opendatatools/futures/futures_agent.py
opendatatools/futures/futures_interface.py
opendatatools/fx/__init__.py
opendatatools/fx/chinamoney_agent.py
opendatatools/fx/fx_interface.py
opendatatools/gaokao/__init__.py
opendatatools/gaokao/gaokao_agent.py
opendatatools/gaokao/gaokao_interface.py
opendatatools/hedgefund/__init__.py
opendatatools/hedgefund/hedgefund_interface.py
opendatatools/hedgefund/simu_agent.py
opendatatools/hsgt/__init__.py
opendatatools/hsgt/hkex_agent.py
opendatatools/hsgt/hsgt_agent.py
opendatatools/hsgt/hsgt_interface.py
opendatatools/index/__init__.py
opendatatools/index/index_agent.py
opendatatools/index/index_interface.py
opendatatools/misc/__init__.py
opendatatools/misc/gaokao_agent.py
opendatatools/movie/__init__.py
opendatatools/movie/movie_agent.py
opendatatools/movie/movie_interface.py
opendatatools/nhindex/__init__.py
opendatatools/nhindex/nhindex_agent.py
